statezero/__init__.py
statezero/adaptors/__init__.py
statezero/adaptors/django/__init__.py
statezero/adaptors/django/action_serializers.py
statezero/adaptors/django/actions.py
statezero/adaptors/django/apps.py
statezero/adaptors/django/config.py
statezero/adaptors/django/context_manager.py
statezero/adaptors/django/db_telemetry.py
statezero/adaptors/django/event_emitters.py
statezero/adaptors/django/exception_handler.py
statezero/adaptors/django/f_handler.py
statezero/adaptors/django/helpers.py
statezero/adaptors/django/middleware.py
statezero/adaptors/django/orm.py
statezero/adaptors/django/permissions.py
statezero/adaptors/django/query_optimizer.py
statezero/adaptors/django/schemas.py
statezero/adaptors/django/serializers.py
statezero/adaptors/django/signals.py
statezero/adaptors/django/urls.py
statezero/adaptors/django/utils.py
statezero/adaptors/django/views.py
statezero/adaptors/django/extensions/__init__.py
statezero/adaptors/django/extensions/simple_history.py
statezero/adaptors/django/extensions/custom_field_serializers/__init__.py
statezero/adaptors/django/extensions/custom_field_serializers/file_fields.py
statezero/adaptors/django/extensions/custom_field_serializers/money_field.py
statezero/adaptors/django/extensions/custom_field_serializers/pydantic_field.py
statezero/adaptors/django/migrations/0001_initial.py
statezero/adaptors/django/migrations/0002_delete_modelviewsubscription.py
statezero/adaptors/django/migrations/__init__.py
statezero/adaptors/django/search_providers/__init__.py
statezero/adaptors/django/search_providers/basic_search.py
statezero/adaptors/django/search_providers/postgres_search.py
statezero/core/__init__.py
statezero/core/actions.py
statezero/core/ast_parser.py
statezero/core/ast_validator.py
statezero/core/classes.py
statezero/core/config.py
statezero/core/context_storage.py
statezero/core/event_bus.py
statezero/core/event_emitters.py
statezero/core/exceptions.py
statezero/core/hook_checks.py
statezero/core/interfaces.py
statezero-0.1.0b60.dist-info/METADATA
statezero-0.1.0b60.dist-info/WHEEL
statezero-0.1.0b60.dist-info/top_level.txt
statezero-0.1.0b60.dist-info/RECORD
