Metadata-Version: 2.4
Name: statezero
Version: 0.1.0b60
Summary: Connect your Python backend to a modern JavaScript SPA frontend with 90% less complexity.
Author-email: Robert <robert.herring@statezero.dev>
Project-URL: homepage, https://www.statezero.dev
Project-URL: repository, https://github.com/state-zero/statezero
Requires-Python: >=3.10
Requires-Dist: Django<5.2.0,>=5.1.0
Requires-Dist: django-money<3.5.0,>=3.4.0
Requires-Dist: djangorestframework<3.16.0,>=3.15.0
Requires-Dist: fakeredis<3.0.0,>=2.27.0
Requires-Dist: fastapi<0.116.0,>=0.115.0
Requires-Dist: hypothesis<7.0.0,>=6.108.0
Requires-Dist: jsonschema<5.0.0,>=4.23.0
Requires-Dist: networkx<4.0.0,>=3.4.0
Requires-Dist: openapi-spec-validator<0.8.0,>=0.7.0
Requires-Dist: orjson<4.0.0,>=3.10.0
Requires-Dist: pusher<4.0.0,>=3.3.0
Requires-Dist: pydantic<3.0.0,>=2.10.0
Requires-Dist: rich<14.0.0,>=13.9.0
Requires-Dist: psycopg2<3.0.0,>=2.9.0
Requires-Dist: django-redis<6.0.0,>=5.4.0
Requires-Dist: django-cors-headers<5.0.0,>=4.7.0
Requires-Dist: django-zen-queries<3.0.0,>=2.1.0
Requires-Dist: cytoolz<2.0.0,>=1.0.0
Requires-Dist: docstring-parser<0.18,>=0.17
